src/topsis.py
topsis_shiti_102003101-1.0.0.dist-info/METADATA
topsis_shiti_102003101-1.0.0.dist-info/WHEEL
topsis_shiti_102003101-1.0.0.dist-info/entry_points.txt
topsis_shiti_102003101-1.0.0.dist-info/top_level.txt
topsis_shiti_102003101-1.0.0.dist-info/RECORD
